pqbit/__init__.py
pqbit/benchmark.py
pqbit/benchmark_routes.py
pqbit/cli.py
pqbit/dilithium.py
pqbit/falcon.py
pqbit/guardian.py
pqbit/kyber.py
pqbit/log_benchmark.py
pqbit/log_viewer.py
pqbit/mesh.yaml
pqbit/obfs4.py
pqbit/pqclean.py
pqbit/pysocks.py
pqbit/report.py
pqbit/simulation.py
pqbit/tunnel.py
pqbit/verifier.py
pqbit/wallet.py
pqbit/wg-meshconf.py
pqbit/wireguard.py
pqbit/wireshark.py
pqbit/cli/__init__.py
pqbit/core/__init__.py
pqbit/mesh/__init__.py
pqbit/utils/__init__.py
pqbit/wallet/__init__.py
pqbit-1.4.0.dist-info/licenses/LICENSE
pqbit-1.4.0.dist-info/METADATA
pqbit-1.4.0.dist-info/WHEEL
pqbit-1.4.0.dist-info/entry_points.txt
pqbit-1.4.0.dist-info/top_level.txt
pqbit-1.4.0.dist-info/RECORD
