Metadata-Version: 2.4
Name: pqbit
Version: 1.4.0
Summary: Post-quantum mesh VPN library with offline wallet generation via Falcon-1024, Dilithium5 and SHA3-512
Home-page: https://github.com/kitohamachi/pqbit
Author: Kito Hamachi
Author-email: kitohamachi@hotmail.com
License: MIT
Classifier: Programming Language :: Python :: 3
Classifier: License :: OSI Approved :: MIT License
Classifier: Operating System :: OS Independent
Requires-Python: >=3.8
License-File: LICENSE
Requires-Dist: pypqc>=0.0.6.2
Requires-Dist: pyshark>=0.6
Requires-Dist: scapy>=2.5.0
Requires-Dist: wg-meshconf>=2.5.1
Requires-Dist: wireguard>=1.0.2
Requires-Dist: wireguard4netns>=0.1.6
Requires-Dist: pytest>=8.4.2
Requires-Dist: PyYAML>=6.0
Requires-Dist: PySocks>=1.7.1
Requires-Dist: qrcode[pil]>=7.4.2
Requires-Dist: cffi>=2.0.0
Requires-Dist: pycparser>=2.23
Requires-Dist: logging4>=0.0.2
Dynamic: author
Dynamic: author-email
Dynamic: classifier
Dynamic: description
Dynamic: description-content-type
Dynamic: home-page
Dynamic: license-file
Dynamic: requires-dist
Dynamic: requires-python
Dynamic: summary
